[
  {
    "raison_sociale": "ECB OLIVIER MARTIN",
    "agrement": "E1000236020",
    "adresse": "35 rue de Picardie",
    "cp": "2420",
    "ville": "BELLICOURT",
    "tauxa1": "",
    "tauxa2": "",
    "tauxb": "61,63%",
    "tauxb1": "",
    "tauxbe": "",
    "tauxc1": "",
    "tauxce": "",
    "tauxd": "",
    "label_qualite": "",
    "permis_1euro_jour": "",
    "permis_A": "",
    "permis_A1": "",
    "permis_A2": "",
    "permis_B": "",
    "permis_BE": "",
    "permis_C": "",
    "permis_C1": "",
    "permis_CE": "",
    "permis_C1E": "",
    "permis_D": "",
    "permis_D1": "",
    "permis_DE": "",
    "lng": "3.231365",
    "lat": 49.961701
  }
]