[
  {
    "raison_sociale": "A-E LA BRUYERE MOTO PASSION",
    "agrement": "E0300102860",
    "adresse": "56 RUE CHARLES ROBIN",
    "cp": "1000",
    "ville": "BOURG EN BRESSE",
    "tauxa1": "",
    "tauxa2": "",
    "tauxb": "65,22%",
    "tauxb1": "",
    "tauxbe": "",
    "tauxc1": "",
    "tauxce": "",
    "tauxd": "",
    "label_qualite": "",
    "permis_1euro_jour": "",
    "permis_A": "",
    "permis_A1": "",
    "permis_A2": "",
    "permis_B": "",
    "permis_BE": "",
    "permis_C": "",
    "permis_C1": "",
    "permis_CE": "",
    "permis_C1E": "",
    "permis_D": "",
    "permis_D1": "",
    "permis_DE": "",
    "lng": "5.233508",
    "lat": 46.2059045
  },
  {
    "raison_sociale": "DES LYCEES",
    "agrement": "E0600104060",
    "adresse": "6 RUE DU LYCEE",
    "cp": "1000",
    "ville": "BOURG EN BRESSE",
    "tauxa1": "",
    "tauxa2": "",
    "tauxb": "38,89%",
    "tauxb1": "",
    "tauxbe": "",
    "tauxc1": "",
    "tauxce": "",
    "tauxd": "",
    "label_qualite": "Oui",
    "permis_1euro_jour": "Non",
    "permis_A": "Non",
    "permis_A1": "Non",
    "permis_A2": "Non",
    "permis_B": "Oui",
    "permis_BE": "Non",
    "permis_C": "Non",
    "permis_C1": "Non",
    "permis_CE": "Non",
    "permis_C1E": "Non",
    "permis_D": "Non",
    "permis_D1": "Non",
    "permis_DE": "Non",
    "lng": "5.2260366",
    "lat": 46.2029715
  },
  {
    "raison_sociale": "LA PASSERELLE",
    "agrement": "E1800100130",
    "adresse": "27 avenue Jean Jaurès",
    "cp": "1000",
    "ville": "BOURG EN BRESSE",
    "tauxa1": "",
    "tauxa2": "100,00%",
    "tauxb": "60,61%",
    "tauxb1": "",
    "tauxbe": "0,00%",
    "tauxc1": "",
    "tauxce": "",
    "tauxd": "",
    "label_qualite": "",
    "permis_1euro_jour": "",
    "permis_A": "",
    "permis_A1": "",
    "permis_A2": "",
    "permis_B": "",
    "permis_BE": "",
    "permis_C": "",
    "permis_C1": "",
    "permis_CE": "",
    "permis_C1E": "",
    "permis_D": "",
    "permis_D1": "",
    "permis_DE": "",
    "lng": "5.2184253",
    "lat": 46.199679
  },
  {
    "raison_sociale": "DE LA GARE",
    "agrement": "E1500100010",
    "adresse": "9 avenue Pierre Sémard",
    "cp": "1000",
    "ville": "BOURG EN BRESSE",
    "tauxa1": "",
    "tauxa2": "100,00%",
    "tauxb": "57,89%",
    "tauxb1": "",
    "tauxbe": "100,00%",
    "tauxc1": "",
    "tauxce": "",
    "tauxd": "",
    "label_qualite": "Oui",
    "permis_1euro_jour": "Oui",
    "permis_A": "Non",
    "permis_A1": "Non",
    "permis_A2": "Non",
    "permis_B": "Oui",
    "permis_BE": "Non",
    "permis_C": "Non",
    "permis_C1": "Non",
    "permis_CE": "Non",
    "permis_C1E": "Non",
    "permis_D": "Non",
    "permis_D1": "Non",
    "permis_DE": "Non",
    "lng": "5.2154649",
    "lat": 46.200662
  },
  {
    "raison_sociale": "EUROP",
    "agrement": "E0600104000",
    "adresse": "3 RUE DE LA REPUBLIQUE",
    "cp": "1000",
    "ville": "BOURG EN BRESSE",
    "tauxa1": "",
    "tauxa2": "",
    "tauxb": "53,85%",
    "tauxb1": "",
    "tauxbe": "",
    "tauxc1": "",
    "tauxce": "",
    "tauxd": "",
    "label_qualite": "",
    "permis_1euro_jour": "",
    "permis_A": "",
    "permis_A1": "",
    "permis_A2": "",
    "permis_B": "",
    "permis_BE": "",
    "permis_C": "",
    "permis_C1": "",
    "permis_CE": "",
    "permis_C1E": "",
    "permis_D": "",
    "permis_D1": "",
    "permis_DE": "",
    "lng": "5.2269218",
    "lat": 46.2034216
  },
  {
    "raison_sociale": "LA PASSERELLE",
    "agrement": "E1300100130",
    "adresse": "27 Avenue Jean Jaures",
    "cp": "1000",
    "ville": "BOURG EN BRESSE",
    "tauxa1": "",
    "tauxa2": "92,00%",
    "tauxb": "49,18%",
    "tauxb1": "",
    "tauxbe": "88,89%",
    "tauxc1": "",
    "tauxce": "",
    "tauxd": "",
    "label_qualite": "",
    "permis_1euro_jour": "",
    "permis_A": "",
    "permis_A1": "",
    "permis_A2": "",
    "permis_B": "",
    "permis_BE": "",
    "permis_C": "",
    "permis_C1": "",
    "permis_CE": "",
    "permis_C1E": "",
    "permis_D": "",
    "permis_D1": "",
    "permis_DE": "",
    "lng": "5.2184253",
    "lat": 46.199679
  },
  {
    "raison_sociale": "PATOU BRESSE REVERMONT BOURG",
    "agrement": "E1500100030",
    "adresse": "37 boulevard Victor Hugo",
    "cp": "1000",
    "ville": "BOURG EN BRESSE",
    "tauxa1": "",
    "tauxa2": "",
    "tauxb": "90,91%",
    "tauxb1": "",
    "tauxbe": "",
    "tauxc1": "",
    "tauxce": "",
    "tauxd": "",
    "label_qualite": "",
    "permis_1euro_jour": "",
    "permis_A": "",
    "permis_A1": "",
    "permis_A2": "",
    "permis_B": "",
    "permis_BE": "",
    "permis_C": "",
    "permis_C1": "",
    "permis_CE": "",
    "permis_C1E": "",
    "permis_D": "",
    "permis_D1": "",
    "permis_DE": "",
    "lng": "5.2304648",
    "lat": 46.2017202
  },
  {
    "raison_sociale": "POLYTECHNIQUE",
    "agrement": "E1400100150",
    "adresse": "8 rue du 4 Septembre",
    "cp": "1000",
    "ville": "BOURG EN BRESSE",
    "tauxa1": "",
    "tauxa2": "",
    "tauxb": "58,33%",
    "tauxb1": "",
    "tauxbe": "",
    "tauxc1": "",
    "tauxce": "",
    "tauxd": "",
    "label_qualite": "",
    "permis_1euro_jour": "",
    "permis_A": "",
    "permis_A1": "",
    "permis_A2": "",
    "permis_B": "",
    "permis_BE": "",
    "permis_C": "",
    "permis_C1": "",
    "permis_CE": "",
    "permis_C1E": "",
    "permis_D": "",
    "permis_D1": "",
    "permis_DE": "",
    "lng": "5.2290695",
    "lat": 46.2059489
  },
  {
    "raison_sociale": "POLYTECHNIQUE",
    "agrement": "E1800100030",
    "adresse": "47 rue Charles Robin",
    "cp": "1000",
    "ville": "BOURG EN BRESSE",
    "tauxa1": "",
    "tauxa2": "",
    "tauxb": "55,32%",
    "tauxb1": "",
    "tauxbe": "",
    "tauxc1": "",
    "tauxce": "",
    "tauxd": "",
    "label_qualite": "",
    "permis_1euro_jour": "",
    "permis_A": "",
    "permis_A1": "",
    "permis_A2": "",
    "permis_B": "",
    "permis_BE": "",
    "permis_C": "",
    "permis_C1": "",
    "permis_CE": "",
    "permis_C1E": "",
    "permis_D": "",
    "permis_D1": "",
    "permis_DE": "",
    "lng": "5.2308136",
    "lat": 46.2057623
  },
  {
    "raison_sociale": "ROM'AIN",
    "agrement": "E1300100040",
    "adresse": "47 rue Charles Robin",
    "cp": "1000",
    "ville": "BOURG EN BRESSE",
    "tauxa1": "",
    "tauxa2": "",
    "tauxb": "100,00%",
    "tauxb1": "",
    "tauxbe": "",
    "tauxc1": "",
    "tauxce": "",
    "tauxd": "",
    "label_qualite": "",
    "permis_1euro_jour": "",
    "permis_A": "",
    "permis_A1": "",
    "permis_A2": "",
    "permis_B": "",
    "permis_BE": "",
    "permis_C": "",
    "permis_C1": "",
    "permis_CE": "",
    "permis_C1E": "",
    "permis_D": "",
    "permis_D1": "",
    "permis_DE": "",
    "lng": "5.2308136",
    "lat": 46.2057623
  },
  {
    "raison_sociale": "SARL CFSR SUZON",
    "agrement": "E0300103750",
    "adresse": "2 RUE DU LYCEE",
    "cp": "1000",
    "ville": "BOURG EN BRESSE",
    "tauxa1": "75,00%",
    "tauxa2": "93,90%",
    "tauxb": "66,73%",
    "tauxb1": "",
    "tauxbe": "",
    "tauxc1": "",
    "tauxce": "",
    "tauxd": "",
    "label_qualite": "",
    "permis_1euro_jour": "",
    "permis_A": "",
    "permis_A1": "",
    "permis_A2": "",
    "permis_B": "",
    "permis_BE": "",
    "permis_C": "",
    "permis_C1": "",
    "permis_CE": "",
    "permis_C1E": "",
    "permis_D": "",
    "permis_D1": "",
    "permis_DE": "",
    "lng": "5.2259957",
    "lat": 46.2017258
  },
  {
    "raison_sociale": "TRAJECTOIRE",
    "agrement": "E1500100150",
    "adresse": "11 Avenue Alphonse Muscat",
    "cp": "1000",
    "ville": "BOURG EN BRESSE",
    "tauxa1": "100,00%",
    "tauxa2": "87,50%",
    "tauxb": "55,47%",
    "tauxb1": "",
    "tauxbe": "",
    "tauxc1": "",
    "tauxce": "",
    "tauxd": "",
    "label_qualite": "",
    "permis_1euro_jour": "",
    "permis_A": "",
    "permis_A1": "",
    "permis_A2": "",
    "permis_B": "",
    "permis_BE": "",
    "permis_C": "",
    "permis_C1": "",
    "permis_CE": "",
    "permis_C1E": "",
    "permis_D": "",
    "permis_D1": "",
    "permis_DE": "",
    "lng": "5.2191773",
    "lat": 46.2027302
  }
]