[
  {
    "raison_sociale": "ECF Sud Prévention Sécurité",
    "agrement": "E1208311450",
    "adresse": "ZI des Consacs",
    "cp": "83170",
    "ville": "Brignoles",
    "tauxa1": "",
    "tauxa2": "",
    "tauxb": "",
    "tauxb1": "",
    "tauxbe": "66,67%",
    "tauxc1": "93,75%",
    "tauxce": "83,33%",
    "tauxd": "",
    "label_qualite": "",
    "permis_1euro_jour": "",
    "permis_A": "",
    "permis_A1": "",
    "permis_A2": "",
    "permis_B": "",
    "permis_BE": "",
    "permis_C": "",
    "permis_C1": "",
    "permis_CE": "",
    "permis_C1E": "",
    "permis_D": "",
    "permis_D1": "",
    "permis_DE": "",
    "lng": "6.0460778",
    "lat": 43.4026297
  },
  {
    "raison_sociale": "Athena conduite",
    "agrement": "E1508300140",
    "adresse": "11 rue d'Entraigues",
    "cp": "83170",
    "ville": "BRIGNOLES",
    "tauxa1": "",
    "tauxa2": "",
    "tauxb": "46,21%",
    "tauxb1": "",
    "tauxbe": "",
    "tauxc1": "",
    "tauxce": "",
    "tauxd": "",
    "label_qualite": "",
    "permis_1euro_jour": "",
    "permis_A": "",
    "permis_A1": "",
    "permis_A2": "",
    "permis_B": "",
    "permis_BE": "",
    "permis_C": "",
    "permis_C1": "",
    "permis_CE": "",
    "permis_C1E": "",
    "permis_D": "",
    "permis_D1": "",
    "permis_DE": "",
    "lng": "6.0607753",
    "lat": 43.4055982
  },
  {
    "raison_sociale": "EASY CONDUITE 83",
    "agrement": "E1608300200",
    "adresse": "11 AV MARECHAL FOCH",
    "cp": "83170",
    "ville": "BRIGNOLES",
    "tauxa1": "",
    "tauxa2": "",
    "tauxb": "48,46%",
    "tauxb1": "",
    "tauxbe": "",
    "tauxc1": "",
    "tauxce": "",
    "tauxd": "",
    "label_qualite": "",
    "permis_1euro_jour": "",
    "permis_A": "",
    "permis_A1": "",
    "permis_A2": "",
    "permis_B": "",
    "permis_BE": "",
    "permis_C": "",
    "permis_C1": "",
    "permis_CE": "",
    "permis_C1E": "",
    "permis_D": "",
    "permis_D1": "",
    "permis_DE": "",
    "lng": "6.0666487",
    "lat": 43.4078856
  },
  {
    "raison_sociale": "ECF du Lycée",
    "agrement": "E1508300050",
    "adresse": "avenue des Martyrs de la Résistance",
    "cp": "83170",
    "ville": "Brignoles",
    "tauxa1": "",
    "tauxa2": "96,00%",
    "tauxb": "48,02%",
    "tauxb1": "",
    "tauxbe": "33,33%",
    "tauxc1": "",
    "tauxce": "",
    "tauxd": "",
    "label_qualite": "",
    "permis_1euro_jour": "",
    "permis_A": "",
    "permis_A1": "",
    "permis_A2": "",
    "permis_B": "",
    "permis_BE": "",
    "permis_C": "",
    "permis_C1": "",
    "permis_CE": "",
    "permis_C1E": "",
    "permis_D": "",
    "permis_D1": "",
    "permis_DE": "",
    "lng": "6.0636727",
    "lat": 43.4098605
  },
  {
    "raison_sociale": "ECF-SPS GRAND PUBLIC",
    "agrement": "E1808300090",
    "adresse": "avenue des martyrs de la résistance",
    "cp": "83170",
    "ville": "Brignoles",
    "tauxa1": "100,00%",
    "tauxa2": "96,97%",
    "tauxb": "51,23%",
    "tauxb1": "",
    "tauxbe": "",
    "tauxc1": "",
    "tauxce": "100,00%",
    "tauxd": "",
    "label_qualite": "",
    "permis_1euro_jour": "",
    "permis_A": "",
    "permis_A1": "",
    "permis_A2": "",
    "permis_B": "",
    "permis_BE": "",
    "permis_C": "",
    "permis_C1": "",
    "permis_CE": "",
    "permis_C1E": "",
    "permis_D": "",
    "permis_D1": "",
    "permis_DE": "",
    "lng": "6.0636727",
    "lat": 43.4098605
  },
  {
    "raison_sociale": "RICHARD Formation",
    "agrement": "E0808310550",
    "adresse": "7 bd Just-Marie RAYNOUARD",
    "cp": "83170",
    "ville": "BRIGNOLES",
    "tauxa1": "",
    "tauxa2": "",
    "tauxb": "",
    "tauxb1": "",
    "tauxbe": "60,00%",
    "tauxc1": "74,81%",
    "tauxce": "100,00%",
    "tauxd": "70,00%",
    "label_qualite": "",
    "permis_1euro_jour": "",
    "permis_A": "",
    "permis_A1": "",
    "permis_A2": "",
    "permis_B": "",
    "permis_BE": "",
    "permis_C": "",
    "permis_C1": "",
    "permis_CE": "",
    "permis_C1E": "",
    "permis_D": "",
    "permis_D1": "",
    "permis_DE": "",
    "lng": "6.0732475",
    "lat": 43.4083047
  },
  {
    "agrement": "E2008300030",
    "raison_sociale": "SARL CONNECT CONDUITE GROUP",
    "adresse": "128 AVENUE SAINT JEAN",
    "cp": 83170,
    "tauxa1": "",
    "tauxa2": "",
    "tauxb": "",
    "tauxb1": "",
    "tauxbe": "",
    "tauxc1": "",
    "tauxce": "",
    "tauxd": "",
    "ville": "BRIGNOLES",
    "label_qualite": "Oui",
    "permis_1euro_jour": "Oui",
    "permis_A": "Oui",
    "permis_A1": "Oui",
    "permis_A2": "Oui",
    "permis_B": "Oui",
    "permis_BE": "Non",
    "permis_C": "Non",
    "permis_C1": "Non",
    "permis_CE": "Non",
    "permis_C1E": "Non",
    "permis_D": "Non",
    "permis_D1": "Non",
    "permis_DE": "Non",
    "lng": "6.0535035",
    "lat": 43.407407
  }
]