[
  {
    "raison_sociale": "POLE PIC",
    "agrement": "E1306900320",
    "adresse": "6 rue Paul Pic",
    "cp": "69500",
    "ville": "Bron",
    "tauxa1": "",
    "tauxa2": "",
    "tauxb": "44,97%",
    "tauxb1": "",
    "tauxbe": "",
    "tauxc1": "",
    "tauxce": "",
    "tauxd": "",
    "label_qualite": "",
    "permis_1euro_jour": "",
    "permis_A": "",
    "permis_A1": "",
    "permis_A2": "",
    "permis_B": "",
    "permis_BE": "",
    "permis_C": "",
    "permis_C1": "",
    "permis_CE": "",
    "permis_C1E": "",
    "permis_D": "",
    "permis_D1": "",
    "permis_DE": "",
    "lng": "4.9027858",
    "lat": 45.7295075
  }
]7317966
  },
  {
    "raison_sociale": "BRONDILLANTE",
    "agrement": "E1606900160",
    "adresse": "204 avenue Franklin Roosevelt",
    "cp": "69500",
    "ville": "BRON",
    "tauxa1": "",
    "tauxa2": "",
    "tauxb": "41,94%",
    "tauxb1": "",
    "tauxbe": "",
    "tauxc1": "",
    "tauxce": "",
    "tauxd": "",
    "label_qualite": "",
    "permis_1euro_jour": "",
    "permis_A": "",
    "permis_A1": "",
    "permis_A2": "",
    "permis_B": "",
    "permis_BE": "",
    "permis_C": "",
    "permis_C1": "",
    "permis_CE": "",
    "permis_C1E": "",
    "permis_D": "",
    "permis_D1": "",
    "permis_DE": "",
    "lng": "4.9137074",
    "lat": 45.7317384
  },
  {
    "raison_sociale": "CARAVELLE BRON",
    "agrement": "E1806900030",
    "adresse": "324 route de Genas",
    "cp": "69500",
    "ville": "BRON",
    "tauxa1": "",
    "tauxa2": "",
    "tauxb": "",
    "tauxb1": "",
    "tauxbe": "",
    "tauxc1": "",
    "tauxce": "",
    "tauxd": "",
    "label_qualite": "",
    "permis_1euro_jour": "",
    "permis_A": "",
    "permis_A1": "",
    "permis_A2": "",
    "permis_B": "",
    "permis_BE": "",
    "permis_C": "",
    "permis_C1": "",
    "permis_CE": "",
    "permis_C1E": "",
    "permis_D": "",
    "permis_D1": "",
    "permis_DE": "",
    "lng": "4.9134343",
    "lat": 45.7494394
  },
  {
    "raison_sociale": "SAINT MICHEL",
    "agrement": "E1806900210",
    "adresse": "148 rue de la pagère",
    "cp": "69500",
    "ville": "BRON",
    "tauxa1": "",
    "tauxa2": "100,00%",
    "tauxb": "49,02%",
    "tauxb1": "",
    "tauxbe": "",
    "tauxc1": "",
    "tauxce": "",
    "tauxd": "",
    "label_qualite": "Oui",
    "permis_1euro_jour": "Oui",
    "permis_A": "Oui",
    "permis_A1": "Oui",
    "permis_A2": "Oui",
    "permis_B": "Oui",
    "permis_BE": "Oui",
    "permis_C": "Non",
    "permis_C1": "Non",
    "permis_CE": "Non",
    "permis_C1E": "Non",
    "permis_D": "Non",
    "permis_D1": "Non",
    "permis_DE": "Non",
    "lng": "4.9160254",
    "lat": 45.7376863
  },
  {
    "raison_sociale": "YOUPIII",
    "agrement": "E1606900340",
    "adresse": "8 rue Eugene Guillemin",
    "cp": "69500",
    "ville": "BRON",
    "tauxa1": "",
    "tauxa2": "",
    "tauxb": "41,82%",
    "tauxb1": "",
    "tauxbe": "",
    "tauxc1": "",
    "tauxce": "",
    "tauxd": "",
    "label_qualite": "Oui",
    "permis_1euro_jour": "Non",
    "permis_A": "Non",
    "permis_A1": "Non",
    "permis_A2": "Non",
    "permis_B": "Oui",
    "permis_BE": "Non",
    "permis_C": "Non",
    "permis_C1": "Non",
    "permis_CE": "Non",
    "permis_C1E": "Non",
    "permis_D": "Non",
    "permis_D1": "Non",
    "permis_DE": "Non",
    "lng": "4.9125107",
    "lat": 45.7328888
  },
  {
    "raison_sociale": "ZZCARAVELLE",
    "agrement": "E1006911930",
    "adresse": "324 route de Genas",
    "cp": "69500",
    "ville": "BRON",
    "tauxa1": "",
    "tauxa2": "100,00%",
    "tauxb": "38,55%",
    "tauxb1": "",
    "tauxbe": "",
    "tauxc1": "",
    "tauxce": "",
    "tauxd": "",
    "label_qualite": "",
    "permis_1euro_jour": "",
    "permis_A": "",
    "permis_A1": "",
    "permis_A2": "",
    "permis_B": "",
    "permis_BE": "",
    "permis_C": "",
    "permis_C1": "",
    "permis_CE": "",
    "permis_C1E": "",
    "permis_D": "",
    "permis_D1": "",
    "permis_DE": "",
    "lng": "4.9134343",
    "lat": 45.7494394
  },
  {
    "raison_sociale": "ZZSAINT MICHEL",
    "agrement": "E0206907410",
    "adresse": "148 150 RUE DE LA PAGERE",
    "cp": "69500",
    "ville": "BRON",
    "tauxa1": "",
    "tauxa2": "90,91%",
    "tauxb": "50,60%",
    "tauxb1": "",
    "tauxbe": "",
    "tauxc1": "",
    "tauxce": "",
    "tauxd": "",
    "label_qualite": "",
    "permis_1euro_jour": "",
    "permis_A": "",
    "permis_A1": "",
    "permis_A2": "",
    "permis_B": "",
    "permis_BE": "",
    "permis_C": "",
    "permis_C1": "",
    "permis_CE": "",
    "permis_C1E": "",
    "permis_D": "",
    "permis_D1": "",
    "permis_DE": "",
    "lng": "4.9144844",
    "lat": 45.7485838
  },
  {
    "raison_sociale": "ZZTERRAILLON",
    "agrement": "E1706900250",
    "adresse": "74 rue Marcel Bramet",
    "cp": "69500",
    "ville": "BRON",
    "tauxa1": "",
    "tauxa2": "",
    "tauxb": "47,37%",
    "tauxb1": "",
    "tauxbe": "",
    "tauxc1": "",
    "tauxce": "",
    "tauxd": "",
    "label_qualite": "",
    "permis_1euro_jour": "",
    "permis_A": "",
    "permis_A1": "",
    "permis_A2": "",
    "permis_B": "",
    "permis_BE": "",
    "permis_C": "",
    "permis_C1": "",
    "permis_CE": "",
    "permis_C1E": "",
    "permis_D": "",
    "permis_D1": "",
    "permis_DE": "",
    "lng": "4.9203588",
    "lat": 45.7431225
  },
  {
    "agrement": "E1806900030",
    "raison_sociale": "CARAVELLE",
    "adresse": "324 ROUTE DE GENAS",
    "cp": 69500,
    "tauxa1": "",
    "tauxa2": "",
    "tauxb": "",
    "tauxb1": "",
    "tauxbe": "",
    "tauxc1": "",
    "tauxce": "",
    "tauxd": "",
    "ville": "BRON",
    "label_qualite": "Oui",
    "permis_1euro_jour": "Oui",
    "permis_A": "Oui",
    "permis_A1": "Oui",
    "permis_A2": "Oui",
    "permis_B": "Oui",
    "permis_BE": "Non",
    "permis_C": "Non",
    "permis_C1": "Non",
    "permis_CE": "Non",
    "permis_C1E": "Non",
    "permis_D": "Non",
    "permis_D1": "Non",
    "permis_DE": "Non",
    "lng": "4.9134343",
    "lat": 45.7494394
  },
  {
    "agrement": "E2106900090",
    "raison_sociale": "YOUPIII",
    "adresse": "59 AVENUE CAMILLE ROUSSET",
    "cp": 69500,
    "tauxa1": "",
    "tauxa2": "",
    "tauxb": "",
    "tauxb1": "",
    "tauxbe": "",
    "tauxc1": "",
    "tauxce": "",
    "tauxd": "",
    "ville": "BRON",
    "label_qualite": "Oui",
    "permis_1euro_jour": "Non",
    "permis_A": "Non",
    "permis_A1": "Non",
    "permis_A2": "Non",
    "permis_B": "Oui",
    "permis_BE": "Non",
    "permis_C": "Non",
    "permis_C1": "Non",
    "permis_CE": "Non",
    "permis_C1E": "Non",
    "permis_D": "Non",
    "permis_D1": "Non",
    "permis_DE": "Non",
    "lng": "4.9114039",
    "lat": 45.7358917
  }
]