[
  {
    "raison_sociale": "FORGET FORMATION",
    "agrement": "E1306100050",
    "adresse": "20 Rue de St Germain",
    "cp": "61250",
    "ville": "CONDE SUR SARTHE",
    "tauxa1": "",
    "tauxa2": "",
    "tauxb": "",
    "tauxb1": "",
    "tauxbe": "66,67%",
    "tauxc1": "95,24%",
    "tauxce": "84,00%",
    "tauxd": "100,00%",
    "label_qualite": "",
    "permis_1euro_jour": "",
    "permis_A": "",
    "permis_A1": "",
    "permis_A2": "",
    "permis_B": "",
    "permis_BE": "",
    "permis_C": "",
    "permis_C1": "",
    "permis_CE": "",
    "permis_C1E": "",
    "permis_D": "",
    "permis_D1": "",
    "permis_DE": "",
    "lng": "0.0602459",
    "lat": 48.42675
  }
]