[
  {
    "raison_sociale": "Leure de conduite",
    "agrement": "E1802700080",
    "adresse": "68 rue Pouyer Quertier",
    "cp": "27380",
    "ville": "FLEURY-SUR-ANDELLE",
    "tauxa1": "",
    "tauxa2": "",
    "tauxb": "",
    "tauxb1": "",
    "tauxbe": "",
    "tauxc1": "",
    "tauxce": "",
    "tauxd": "",
    "label_qualite": "",
    "permis_1euro_jour": "",
    "permis_A": "",
    "permis_A1": "",
    "permis_A2": "",
    "permis_B": "",
    "permis_BE": "",
    "permis_C": "",
    "permis_C1": "",
    "permis_CE": "",
    "permis_C1E": "",
    "permis_D": "",
    "permis_D1": "",
    "permis_DE": "",
    "lng": "1.3569173",
    "lat": 49.360681
  },
  {
    "agrement": "E1802700080",
    "raison_sociale": "LEURE DE CONDUITE",
    "adresse": "68 RUE POUYER QUERTIER",
    "cp": 27380,
    "tauxa1": "",
    "tauxa2": "",
    "tauxb": "",
    "tauxb1": "",
    "tauxbe": "",
    "tauxc1": "",
    "tauxce": "",
    "tauxd": "",
    "ville": "FLEURY-SUR-ANDELLE",
    "label_qualite": "Oui",
    "permis_1euro_jour": "Oui",
    "permis_A": "Non",
    "permis_A1": "Non",
    "permis_A2": "Non",
    "permis_B": "Oui",
    "permis_BE": "Non",
    "permis_C": "Non",
    "permis_C1": "Non",
    "permis_CE": "Non",
    "permis_C1E": "Non",
    "permis_D": "Non",
    "permis_D1": "Non",
    "permis_DE": "Non",
    "lng": "1.3569173",
    "lat": 49.360681
  }
]