[
  {
    "raison_sociale": "CER DU LEMAN",
    "agrement": "E1207497870",
    "adresse": "119 rue de Genève",
    "cp": "74240",
    "ville": "GAILLARD",
    "tauxa1": "",
    "tauxa2": "",
    "tauxb": "49,61%",
    "tauxb1": "",
    "tauxbe": "",
    "tauxc1": "",
    "tauxce": "",
    "tauxd": "",
    "label_qualite": "",
    "permis_1euro_jour": "",
    "permis_A": "",
    "permis_A1": "",
    "permis_A2": "",
    "permis_B": "",
    "permis_BE": "",
    "permis_C": "",
    "permis_C1": "",
    "permis_CE": "",
    "permis_C1E": "",
    "permis_D": "",
    "permis_D1": "",
    "permis_DE": "",
    "lng": "6.212450892476215",
    "lat": 46.19137865
  },
  {
    "raison_sociale": "ESR",
    "agrement": "E1807400040",
    "adresse": "58 RUE DE LA LIBERATION",
    "cp": "74240",
    "ville": "GAILLARD",
    "tauxa1": "",
    "tauxa2": "",
    "tauxb": "54,55%",
    "tauxb1": "",
    "tauxbe": "",
    "tauxc1": "",
    "tauxce": "",
    "tauxd": "",
    "label_qualite": "",
    "permis_1euro_jour": "",
    "permis_A": "",
    "permis_A1": "",
    "permis_A2": "",
    "permis_B": "",
    "permis_BE": "",
    "permis_C": "",
    "permis_C1": "",
    "permis_CE": "",
    "permis_C1E": "",
    "permis_D": "",
    "permis_D1": "",
    "permis_DE": "",
    "lng": "6.2120766",
    "lat": 46.1915542
  },
  {
    "agrement": "E0507497390",
    "raison_sociale": "BONNE ROUTE",
    "adresse": "2 RUE DU 18 AOUT",
    "cp": 74240,
    "tauxa1": "",
    "tauxa2": "",
    "tauxb": "",
    "tauxb1": "",
    "tauxbe": "",
    "tauxc1": "",
    "tauxce": "",
    "tauxd": "",
    "ville": "GAILLARD",
    "label_qualite": "Oui",
    "permis_1euro_jour": "Oui",
    "permis_A": "Oui",
    "permis_A1": "Oui",
    "permis_A2": "Oui",
    "permis_B": "Oui",
    "permis_BE": "Non",
    "permis_C": "Non",
    "permis_C1": "Non",
    "permis_CE": "Non",
    "permis_C1E": "Non",
    "permis_D": "Non",
    "permis_D1": "Non",
    "permis_DE": "Non",
    "lng": "6.2120561",
    "lat": 46.186793
  }
]