[
  {
    "raison_sociale": "CONDUITE DE A à Z",
    "agrement": "E1606700020",
    "adresse": "7 C rue de Mundolsheim",
    "cp": "67450",
    "ville": "LAMPERTHEIM",
    "tauxa1": "",
    "tauxa2": "",
    "tauxb": "62,50%",
    "tauxb1": "",
    "tauxbe": "",
    "tauxc1": "",
    "tauxce": "",
    "tauxd": "",
    "label_qualite": "",
    "permis_1euro_jour": "",
    "permis_A": "",
    "permis_A1": "",
    "permis_A2": "",
    "permis_B": "",
    "permis_BE": "",
    "permis_C": "",
    "permis_C1": "",
    "permis_CE": "",
    "permis_C1E": "",
    "permis_D": "",
    "permis_D1": "",
    "permis_DE": "",
    "lng": "7.7019669",
    "lat": 48.6473642
  }
]