[
  {
    "raison_sociale": "- AUTO ECOLE DE LA PASSERELLE",
    "agrement": "E0200203520",
    "adresse": "29 BOULEVARD GRAS BRANCOURT",
    "cp": "2000",
    "ville": "LAON",
    "tauxa1": "",
    "tauxa2": "96,55%",
    "tauxb": "71,05%",
    "tauxb1": "",
    "tauxbe": "",
    "tauxc1": "",
    "tauxce": "",
    "tauxd": "",
    "label_qualite": "",
    "permis_1euro_jour": "",
    "permis_A": "",
    "permis_A1": "",
    "permis_A2": "",
    "permis_B": "",
    "permis_BE": "",
    "permis_C": "",
    "permis_C1": "",
    "permis_CE": "",
    "permis_C1E": "",
    "permis_D": "",
    "permis_D1": "",
    "permis_DE": "",
    "lng": "3.62931",
    "lat": 49.570562
  },
  {
    "raison_sociale": "DEFONTAINE",
    "agrement": "E1700200050",
    "adresse": "2 rue René Liebert",
    "cp": "2000",
    "ville": "LAON",
    "tauxa1": "",
    "tauxa2": "",
    "tauxb": "61,93%",
    "tauxb1": "",
    "tauxbe": "",
    "tauxc1": "",
    "tauxce": "",
    "tauxd": "",
    "label_qualite": "",
    "permis_1euro_jour": "",
    "permis_A": "",
    "permis_A1": "",
    "permis_A2": "",
    "permis_B": "",
    "permis_BE": "",
    "permis_C": "",
    "permis_C1": "",
    "permis_CE": "",
    "permis_C1E": "",
    "permis_D": "",
    "permis_D1": "",
    "permis_DE": "",
    "lng": "3.6388639",
    "lat": 49.5627553
  },
  {
    "raison_sociale": "DEFONTAINE",
    "agrement": "E1200236080",
    "adresse": "61 boulevard de Lyon",
    "cp": "2000",
    "ville": "LAON",
    "tauxa1": "",
    "tauxa2": "",
    "tauxb": "77,27%",
    "tauxb1": "",
    "tauxbe": "",
    "tauxc1": "",
    "tauxce": "",
    "tauxd": "",
    "label_qualite": "",
    "permis_1euro_jour": "",
    "permis_A": "",
    "permis_A1": "",
    "permis_A2": "",
    "permis_B": "",
    "permis_BE": "",
    "permis_C": "",
    "permis_C1": "",
    "permis_CE": "",
    "permis_C1E": "",
    "permis_D": "",
    "permis_D1": "",
    "permis_DE": "",
    "lng": "3.6311146",
    "lat": 49.5690736
  },
  {
    "raison_sociale": "VAUX LAON",
    "agrement": "E1500200030",
    "adresse": "15 rue Fernand THUILLART",
    "cp": "2000",
    "ville": "LAON",
    "tauxa1": "",
    "tauxa2": "",
    "tauxb": "59,59%",
    "tauxb1": "",
    "tauxbe": "",
    "tauxc1": "",
    "tauxce": "",
    "tauxd": "",
    "label_qualite": "",
    "permis_1euro_jour": "",
    "permis_A": "",
    "permis_A1": "",
    "permis_A2": "",
    "permis_B": "",
    "permis_BE": "",
    "permis_C": "",
    "permis_C1": "",
    "permis_CE": "",
    "permis_C1E": "",
    "permis_D": "",
    "permis_D1": "",
    "permis_DE": "",
    "lng": "3.633222",
    "lat": 49.568255
  },
  {
    "raison_sociale": "Auto école CHAMPAGNE",
    "agrement": "E1600200060",
    "adresse": "112 rue Pierre CURTIL",
    "cp": "2000",
    "ville": "LAON",
    "tauxa1": "",
    "tauxa2": "",
    "tauxb": "0,00%",
    "tauxb1": "",
    "tauxbe": "",
    "tauxc1": "",
    "tauxce": "",
    "tauxd": "",
    "label_qualite": "",
    "permis_1euro_jour": "",
    "permis_A": "",
    "permis_A1": "",
    "permis_A2": "",
    "permis_B": "",
    "permis_BE": "",
    "permis_C": "",
    "permis_C1": "",
    "permis_CE": "",
    "permis_C1E": "",
    "permis_D": "",
    "permis_D1": "",
    "permis_DE": "",
    "lng": "3.9667672",
    "lat": 49.4386751
  },
  {
    "raison_sociale": "C - AUTO-ECOLE DU PLATEAU",
    "agrement": "E0200202760",
    "adresse": "3 BIS PLACE VICTOR HUGO",
    "cp": "2000",
    "ville": "LAON",
    "tauxa1": "",
    "tauxa2": "",
    "tauxb": "71,51%",
    "tauxb1": "",
    "tauxbe": "",
    "tauxc1": "",
    "tauxce": "",
    "tauxd": "",
    "label_qualite": "",
    "permis_1euro_jour": "",
    "permis_A": "",
    "permis_A1": "",
    "permis_A2": "",
    "permis_B": "",
    "permis_BE": "",
    "permis_C": "",
    "permis_C1": "",
    "permis_CE": "",
    "permis_C1E": "",
    "permis_D": "",
    "permis_D1": "",
    "permis_DE": "",
    "lng": "3.6369749",
    "lat": 49.5699737
  },
  {
    "raison_sociale": "CONCEPT PERMIS",
    "agrement": "E1500200060",
    "adresse": "1134 avenue Georges POMPIDOU",
    "cp": "2000",
    "ville": "LAON",
    "tauxa1": "100,00%",
    "tauxa2": "100,00%",
    "tauxb": "69,48%",
    "tauxb1": "",
    "tauxbe": "80,00%",
    "tauxc1": "100,00%",
    "tauxce": "",
    "tauxd": "",
    "label_qualite": "",
    "permis_1euro_jour": "",
    "permis_A": "",
    "permis_A1": "",
    "permis_A2": "",
    "permis_B": "",
    "permis_BE": "",
    "permis_C": "",
    "permis_C1": "",
    "permis_CE": "",
    "permis_C1E": "",
    "permis_D": "",
    "permis_D1": "",
    "permis_DE": "",
    "lng": "3.6189673",
    "lat": 49.5494835
  },
  {
    "raison_sociale": "FCPM",
    "agrement": "E1600200030",
    "adresse": "10 bis rue du Bourg",
    "cp": "2000",
    "ville": "LAON",
    "tauxa1": "",
    "tauxa2": "",
    "tauxb": "59,21%",
    "tauxb1": "",
    "tauxbe": "",
    "tauxc1": "",
    "tauxce": "",
    "tauxd": "",
    "label_qualite": "",
    "permis_1euro_jour": "",
    "permis_A": "",
    "permis_A1": "",
    "permis_A2": "",
    "permis_B": "",
    "permis_BE": "",
    "permis_C": "",
    "permis_C1": "",
    "permis_CE": "",
    "permis_C1E": "",
    "permis_D": "",
    "permis_D1": "",
    "permis_DE": "",
    "lng": "3.619844",
    "lat": 49.564538
  },
  {
    "raison_sociale": "MICHELET",
    "agrement": "E0200203040",
    "adresse": "11 RUE DU POINT DU JOUR",
    "cp": "2000",
    "ville": "LAON",
    "tauxa1": "",
    "tauxa2": "",
    "tauxb": "",
    "tauxb1": "",
    "tauxbe": "",
    "tauxc1": "",
    "tauxce": "",
    "tauxd": "",
    "label_qualite": "Oui",
    "permis_1euro_jour": "Oui",
    "permis_A": "Oui",
    "permis_A1": "Oui",
    "permis_A2": "Oui",
    "permis_B": "Oui",
    "permis_BE": "Oui",
    "permis_C": "Non",
    "permis_C1": "Non",
    "permis_CE": "Non",
    "permis_C1E": "Non",
    "permis_D": "Non",
    "permis_D1": "Non",
    "permis_DE": "Non",
    "lng": "3.638089",
    "lat": 49.570224
  },
  {
    "agrement": "E0200203040",
    "raison_sociale": "MICHELET",
    "adresse": "11 RUE DU POINT DU JOUR",
    "cp": 2000,
    "tauxa1": "",
    "tauxa2": "",
    "tauxb": "",
    "tauxb1": "",
    "tauxbe": "",
    "tauxc1": "",
    "tauxce": "",
    "tauxd": "",
    "ville": "LAON",
    "label_qualite": "Oui",
    "permis_1euro_jour": "Oui",
    "permis_A": "Oui",
    "permis_A1": "Oui",
    "permis_A2": "Oui",
    "permis_B": "Oui",
    "permis_BE": "Oui",
    "permis_C": "Non",
    "permis_C1": "Non",
    "permis_CE": "Non",
    "permis_C1E": "Non",
    "permis_D": "Non",
    "permis_D1": "Non",
    "permis_DE": "Non",
    "lng": "3.627557",
    "lat": 49.695133
  },
  {
    "agrement": "E1900200060",
    "raison_sociale": "PASSION CONDUITE",
    "adresse": "2 RUE ROGER SALENGRO",
    "cp": 2000,
    "tauxa1": "",
    "tauxa2": "",
    "tauxb": "",
    "tauxb1": "",
    "tauxbe": "",
    "tauxc1": "",
    "tauxce": "",
    "tauxd": "",
    "ville": "LAON",
    "label_qualite": "Oui",
    "permis_1euro_jour": "Oui",
    "permis_A": "Oui",
    "permis_A1": "Oui",
    "permis_A2": "Oui",
    "permis_B": "Oui",
    "permis_BE": "Oui",
    "permis_C": "Non",
    "permis_C1": "Non",
    "permis_CE": "Non",
    "permis_C1E": "Non",
    "permis_D": "Non",
    "permis_D1": "Non",
    "permis_DE": "Non",
    "lng": "3.624317",
    "lat": 49.568211
  }
]