[
  {
    "raison_sociale": "EUROPE CONDUITE",
    "agrement": "E0205301580",
    "adresse": "15 BIS RUE DU VIEUX ST LOUIS",
    "cp": "53000",
    "ville": "LAVAL",
    "tauxa1": "",
    "tauxa2": "",
    "tauxb": "",
    "tauxb1": "",
    "tauxbe": "",
    "tauxc1": "",
    "tauxce": "",
    "tauxd": "",
    "label_qualite": "Oui",
    "permis_1euro_jour": "Oui",
    "permis_A": "Non",
    "permis_A1": "Non",
    "permis_A2": "Non",
    "permis_B": "Oui",
    "permis_BE": "Non",
    "permis_C": "Non",
    "permis_C1": "Non",
    "permis_CE": "Non",
    "permis_C1E": "Non",
    "permis_D": "Non",
    "permis_D1": "Non",
    "permis_DE": "Non",
    "lng": "-0.7774014",
    "lat": 48.0878202
  },
  {
    "raison_sociale": "CONDUITE AND CO",
    "agrement": "E1505300100",
    "adresse": "111 BIS RUE DE PARIS",
    "cp": "53000",
    "ville": "LAVAL",
    "tauxa1": "",
    "tauxa2": "",
    "tauxb": "",
    "tauxb1": "",
    "tauxbe": "",
    "tauxc1": "",
    "tauxce": "",
    "tauxd": "",
    "label_qualite": "",
    "permis_1euro_jour": "",
    "permis_A": "",
    "permis_A1": "",
    "permis_A2": "",
    "permis_B": "",
    "permis_BE": "",
    "permis_C": "",
    "permis_C1": "",
    "permis_CE": "",
    "permis_C1E": "",
    "permis_D": "",
    "permis_D1": "",
    "permis_DE": "",
    "lng": "-0.7582932",
    "lat": 48.0721162
  },
  {
    "raison_sociale": "GUESNERIE",
    "agrement": "E1705300080",
    "adresse": "10 place du Lieutenant",
    "cp": "53000",
    "ville": "LAVAL",
    "tauxa1": "",
    "tauxa2": "",
    "tauxb": "62,63%",
    "tauxb1": "",
    "tauxbe": "",
    "tauxc1": "",
    "tauxce": "",
    "tauxd": "",
    "label_qualite": "",
    "permis_1euro_jour": "",
    "permis_A": "",
    "permis_A1": "",
    "permis_A2": "",
    "permis_B": "",
    "permis_BE": "",
    "permis_C": "",
    "permis_C1": "",
    "permis_CE": "",
    "permis_C1E": "",
    "permis_D": "",
    "permis_D1": "",
    "permis_DE": "",
    "lng": "-0.767921639665778",
    "lat": 48.0722644
  },
  {
    "raison_sociale": "Auto-école Lebreton",
    "agrement": "E1505300130",
    "adresse": "6rue Renaise",
    "cp": "53000",
    "ville": "LAVAL",
    "tauxa1": "",
    "tauxa2": "",
    "tauxb": "",
    "tauxb1": "",
    "tauxbe": "",
    "tauxc1": "",
    "tauxce": "",
    "tauxd": "",
    "label_qualite": "",
    "permis_1euro_jour": "",
    "permis_A": "",
    "permis_A1": "",
    "permis_A2": "",
    "permis_B": "",
    "permis_BE": "",
    "permis_C": "",
    "permis_C1": "",
    "permis_CE": "",
    "permis_C1E": "",
    "permis_D": "",
    "permis_D1": "",
    "permis_DE": "",
    "lng": "-0.7742936",
    "lat": 48.0689556
  },
  {
    "raison_sociale": "BOURNY",
    "agrement": "E0405301840",
    "adresse": "37 PLACE DE LA COMMUNE",
    "cp": "53000",
    "ville": "LAVAL",
    "tauxa1": "",
    "tauxa2": "",
    "tauxb": "",
    "tauxb1": "",
    "tauxbe": "",
    "tauxc1": "",
    "tauxce": "",
    "tauxd": "",
    "label_qualite": "",
    "permis_1euro_jour": "",
    "permis_A": "",
    "permis_A1": "",
    "permis_A2": "",
    "permis_B": "",
    "permis_BE": "",
    "permis_C": "",
    "permis_C1": "",
    "permis_CE": "",
    "permis_C1E": "",
    "permis_D": "",
    "permis_D1": "",
    "permis_DE": "",
    "lng": "-0.7942354",
    "lat": 48.0618302
  },
  {
    "raison_sociale": "CORDELIERS",
    "agrement": "E0905301910",
    "adresse": "6 RUE DE BRETAGNE",
    "cp": "53000",
    "ville": "LAVAL",
    "tauxa1": "",
    "tauxa2": "",
    "tauxb": "",
    "tauxb1": "",
    "tauxbe": "",
    "tauxc1": "",
    "tauxce": "",
    "tauxd": "",
    "label_qualite": "Oui",
    "permis_1euro_jour": "Oui",
    "permis_A": "Oui",
    "permis_A1": "Oui",
    "permis_A2": "Oui",
    "permis_B": "Oui",
    "permis_BE": "Oui",
    "permis_C": "Non",
    "permis_C1": "Non",
    "permis_CE": "Non",
    "permis_C1E": "Non",
    "permis_D": "Non",
    "permis_D1": "Non",
    "permis_DE": "Non",
    "lng": "-0.7809284",
    "lat": 48.0705259
  },
  {
    "raison_sociale": "DAGUET JEAN LUC",
    "agrement": "E0205301520",
    "adresse": "41 PLACE DE LA TREMOILLE",
    "cp": "53000",
    "ville": "LAVAL",
    "tauxa1": "",
    "tauxa2": "",
    "tauxb": "74,44%",
    "tauxb1": "",
    "tauxbe": "",
    "tauxc1": "",
    "tauxce": "",
    "tauxd": "",
    "label_qualite": "",
    "permis_1euro_jour": "",
    "permis_A": "",
    "permis_A1": "",
    "permis_A2": "",
    "permis_B": "",
    "permis_BE": "",
    "permis_C": "",
    "permis_C1": "",
    "permis_CE": "",
    "permis_C1E": "",
    "permis_D": "",
    "permis_D1": "",
    "permis_DE": "",
    "lng": "-0.7722213",
    "lat": 48.0684969
  },
  {
    "raison_sociale": "Albert",
    "agrement": "E1305300020",
    "adresse": "9 rue Charles Landelle",
    "cp": "53000",
    "ville": "LAVAL",
    "tauxa1": "",
    "tauxa2": "",
    "tauxb": "",
    "tauxb1": "",
    "tauxbe": "",
    "tauxc1": "",
    "tauxce": "",
    "tauxd": "",
    "label_qualite": "",
    "permis_1euro_jour": "",
    "permis_A": "",
    "permis_A1": "",
    "permis_A2": "",
    "permis_B": "",
    "permis_BE": "",
    "permis_C": "",
    "permis_C1": "",
    "permis_CE": "",
    "permis_C1E": "",
    "permis_D": "",
    "permis_D1": "",
    "permis_DE": "",
    "lng": "-0.772732",
    "lat": 48.0681722
  },
  {
    "raison_sociale": "Gaëlle LOIZEAU",
    "agrement": "E1505300050",
    "adresse": "35 rue du Val de Mayenne",
    "cp": "53000",
    "ville": "LAVAL",
    "tauxa1": "",
    "tauxa2": "",
    "tauxb": "66,67%",
    "tauxb1": "",
    "tauxbe": "",
    "tauxc1": "",
    "tauxce": "",
    "tauxd": "",
    "label_qualite": "",
    "permis_1euro_jour": "",
    "permis_A": "",
    "permis_A1": "",
    "permis_A2": "",
    "permis_B": "",
    "permis_BE": "",
    "permis_C": "",
    "permis_C1": "",
    "permis_CE": "",
    "permis_C1E": "",
    "permis_D": "",
    "permis_D1": "",
    "permis_DE": "",
    "lng": "-0.7713812",
    "lat": 48.0693046
  },
  {
    "raison_sociale": "GUESNERIE GHISLAINE",
    "agrement": "E0405301830",
    "adresse": "10 PLACE DU LIEUTENANT",
    "cp": "53000",
    "ville": "LAVAL",
    "tauxa1": "",
    "tauxa2": "",
    "tauxb": "37,50%",
    "tauxb1": "",
    "tauxbe": "",
    "tauxc1": "",
    "tauxce": "",
    "tauxd": "",
    "label_qualite": "",
    "permis_1euro_jour": "",
    "permis_A": "",
    "permis_A1": "",
    "permis_A2": "",
    "permis_B": "",
    "permis_BE": "",
    "permis_C": "",
    "permis_C1": "",
    "permis_CE": "",
    "permis_C1E": "",
    "permis_D": "",
    "permis_D1": "",
    "permis_DE": "",
    "lng": "-0.767921639665778",
    "lat": 48.0722644
  },
  {
    "raison_sociale": "Inser'Conduite 53",
    "agrement": "I1505300010",
    "adresse": "41 rue Crossardière",
    "cp": "53000",
    "ville": "LAVAL",
    "tauxa1": "",
    "tauxa2": "",
    "tauxb": "32,26%",
    "tauxb1": "",
    "tauxbe": "",
    "tauxc1": "",
    "tauxce": "",
    "tauxd": "",
    "label_qualite": "",
    "permis_1euro_jour": "",
    "permis_A": "",
    "permis_A1": "",
    "permis_A2": "",
    "permis_B": "",
    "permis_BE": "",
    "permis_C": "",
    "permis_C1": "",
    "permis_CE": "",
    "permis_C1E": "",
    "permis_D": "",
    "permis_D1": "",
    "permis_DE": "",
    "lng": "-0.763629952011929",
    "lat": 48.07379825
  },
  {
    "raison_sociale": "NJ",
    "agrement": "E0905301970",
    "adresse": "53 rue de la Filature",
    "cp": "53000",
    "ville": "LAVAL",
    "tauxa1": "100,00%",
    "tauxa2": "100,00%",
    "tauxb": "49,40%",
    "tauxb1": "",
    "tauxbe": "",
    "tauxc1": "",
    "tauxce": "",
    "tauxd": "",
    "label_qualite": "",
    "permis_1euro_jour": "",
    "permis_A": "",
    "permis_A1": "",
    "permis_A2": "",
    "permis_B": "",
    "permis_BE": "",
    "permis_C": "",
    "permis_C1": "",
    "permis_CE": "",
    "permis_C1E": "",
    "permis_D": "",
    "permis_D1": "",
    "permis_DE": "",
    "lng": "-0.7725167",
    "lat": 48.0869563
  },
  {
    "agrement": "E1505300130",
    "raison_sociale": "AUTO-ÉCOLE LEBRETON",
    "adresse": "06 RUE RENAISE",
    "cp": 53000,
    "tauxa1": "",
    "tauxa2": "",
    "tauxb": "",
    "tauxb1": "",
    "tauxbe": "",
    "tauxc1": "",
    "tauxce": "",
    "tauxd": "",
    "ville": "LAVAL",
    "label_qualite": "Oui",
    "permis_1euro_jour": "Oui",
    "permis_A": "Non",
    "permis_A1": "Non",
    "permis_A2": "Non",
    "permis_B": "Oui",
    "permis_BE": "Non",
    "permis_C": "Non",
    "permis_C1": "Non",
    "permis_CE": "Non",
    "permis_C1E": "Non",
    "permis_D": "Non",
    "permis_D1": "Non",
    "permis_DE": "Non",
    "lng": "-0.7742936",
    "lat": 48.0689556
  },
  {
    "agrement": "E0405301840",
    "raison_sociale": "BOURNY - ECOLE DE CONDUITE MAYENNAISE",
    "adresse": "37 PLACE DE LA COMMUNE",
    "cp": 53000,
    "tauxa1": "",
    "tauxa2": "",
    "tauxb": "",
    "tauxb1": "",
    "tauxbe": "",
    "tauxc1": "",
    "tauxce": "",
    "tauxd": "",
    "ville": "LAVAL",
    "label_qualite": "Oui",
    "permis_1euro_jour": "Oui",
    "permis_A": "Oui",
    "permis_A1": "Oui",
    "permis_A2": "Oui",
    "permis_B": "Oui",
    "permis_BE": "Oui",
    "permis_C": "Non",
    "permis_C1": "Non",
    "permis_CE": "Non",
    "permis_C1E": "Non",
    "permis_D": "Non",
    "permis_D1": "Non",
    "permis_DE": "Non",
    "lng": "-0.7942354",
    "lat": 48.0618302
  },
  {
    "agrement": "E1505300100",
    "raison_sociale": "CONDUITE AND CO LAVAL  CFSR",
    "adresse": "111 BIS RUE DE PARIS",
    "cp": 53000,
    "tauxa1": "",
    "tauxa2": "",
    "tauxb": "",
    "tauxb1": "",
    "tauxbe": "",
    "tauxc1": "",
    "tauxce": "",
    "tauxd": "",
    "ville": "LAVAL",
    "label_qualite": "Oui",
    "permis_1euro_jour": "Oui",
    "permis_A": "Oui",
    "permis_A1": "Oui",
    "permis_A2": "Oui",
    "permis_B": "Oui",
    "permis_BE": "Oui",
    "permis_C": "Non",
    "permis_C1": "Non",
    "permis_CE": "Non",
    "permis_C1E": "Non",
    "permis_D": "Non",
    "permis_D1": "Non",
    "permis_DE": "Non",
    "lng": "-0.7582932",
    "lat": 48.0721162
  },
  {
    "agrement": "E0905301910",
    "raison_sociale": "CORDELIERS",
    "adresse": "6 RUE DE BRETAGNE",
    "cp": 53000,
    "tauxa1": "",
    "tauxa2": "",
    "tauxb": "",
    "tauxb1": "",
    "tauxbe": "",
    "tauxc1": "",
    "tauxce": "",
    "tauxd": "",
    "ville": "LAVAL",
    "label_qualite": "Oui",
    "permis_1euro_jour": "Oui",
    "permis_A": "Oui",
    "permis_A1": "Oui",
    "permis_A2": "Oui",
    "permis_B": "Oui",
    "permis_BE": "Oui",
    "permis_C": "Non",
    "permis_C1": "Non",
    "permis_CE": "Non",
    "permis_C1E": "Non",
    "permis_D": "Non",
    "permis_D1": "Non",
    "permis_DE": "Non",
    "lng": "-0.7977127",
    "lat": 48.0688282
  },
  {
    "agrement": "E2005300030",
    "raison_sociale": "ECF CER CENTRE ATLANTIQUE",
    "adresse": "35 PLACE JEAN MOULIN",
    "cp": 53000,
    "tauxa1": "",
    "tauxa2": "",
    "tauxb": "",
    "tauxb1": "",
    "tauxbe": "",
    "tauxc1": "",
    "tauxce": "",
    "tauxd": "",
    "ville": "LAVAL",
    "label_qualite": "Oui",
    "permis_1euro_jour": "Oui",
    "permis_A": "Oui",
    "permis_A1": "Oui",
    "permis_A2": "Oui",
    "permis_B": "Oui",
    "permis_BE": "Oui",
    "permis_C": "Oui",
    "permis_C1": "Oui",
    "permis_CE": "Oui",
    "permis_C1E": "Oui",
    "permis_D": "Oui",
    "permis_D1": "Non",
    "permis_DE": "Oui",
    "lng": "-0.765836",
    "lat": 48.070399
  },
  {
    "agrement": "E1305300020",
    "raison_sociale": "ALBERT",
    "adresse": "9 RUE CHARLES LANDELLE",
    "cp": 53000,
    "tauxa1": "",
    "tauxa2": "",
    "tauxb": "",
    "tauxb1": "",
    "tauxbe": "",
    "tauxc1": "",
    "tauxce": "",
    "tauxd": "",
    "ville": "LAVAL",
    "label_qualite": "Oui",
    "permis_1euro_jour": "Oui",
    "permis_A": "Oui",
    "permis_A1": "Oui",
    "permis_A2": "Oui",
    "permis_B": "Oui",
    "permis_BE": "Oui",
    "permis_C": "Non",
    "permis_C1": "Non",
    "permis_CE": "Non",
    "permis_C1E": "Non",
    "permis_D": "Non",
    "permis_D1": "Non",
    "permis_DE": "Non",
    "lng": "-0.772732",
    "lat": 48.0681722
  },
  {
    "agrement": "E0205301580",
    "raison_sociale": "EUROPE CONDUITE",
    "adresse": "15 BIS, DU VIEUX ST LOUIS",
    "cp": 53000,
    "tauxa1": "",
    "tauxa2": "",
    "tauxb": "",
    "tauxb1": "",
    "tauxbe": "",
    "tauxc1": "",
    "tauxce": "",
    "tauxd": "",
    "ville": "LAVAL",
    "label_qualite": "Oui",
    "permis_1euro_jour": "Oui",
    "permis_A": "Non",
    "permis_A1": "Non",
    "permis_A2": "Non",
    "permis_B": "Oui",
    "permis_BE": "Non",
    "permis_C": "Non",
    "permis_C1": "Non",
    "permis_CE": "Non",
    "permis_C1E": "Non",
    "permis_D": "Non",
    "permis_D1": "Non",
    "permis_DE": "Non",
    "lng": "-0.7774014",
    "lat": 48.0878202
  }
]