[
  {
    "raison_sociale": "LABEL CONDUITE",
    "agrement": "E1209509680",
    "adresse": "18 Rue Vivien",
    "cp": "95270",
    "ville": "LUZARCHES",
    "tauxa1": "",
    "tauxa2": "",
    "tauxb": "65,56%",
    "tauxb1": "",
    "tauxbe": "",
    "tauxc1": "",
    "tauxce": "",
    "tauxd": "",
    "label_qualite": "",
    "permis_1euro_jour": "",
    "permis_A": "",
    "permis_A1": "",
    "permis_A2": "",
    "permis_B": "",
    "permis_BE": "",
    "permis_C": "",
    "permis_C1": "",
    "permis_CE": "",
    "permis_C1E": "",
    "permis_D": "",
    "permis_D1": "",
    "permis_DE": "",
    "lng": "2.4210852",
    "lat": 49.1140435
  },
  {
    "raison_sociale": "LUZARCHES",
    "agrement": "E0309508080",
    "adresse": "4 BIS RUE CHARLES DE GAULLE",
    "cp": "95270",
    "ville": "LUZARCHES",
    "tauxa1": "",
    "tauxa2": "",
    "tauxb": "",
    "tauxb1": "",
    "tauxbe": "",
    "tauxc1": "",
    "tauxce": "",
    "tauxd": "",
    "label_qualite": "",
    "permis_1euro_jour": "",
    "permis_A": "",
    "permis_A1": "",
    "permis_A2": "",
    "permis_B": "",
    "permis_BE": "",
    "permis_C": "",
    "permis_C1": "",
    "permis_CE": "",
    "permis_C1E": "",
    "permis_D": "",
    "permis_D1": "",
    "permis_DE": "",
    "lng": "2.4221358",
    "lat": 49.110644
  },
  {
    "agrement": "E0309508080",
    "raison_sociale": "AUTO MOTO ECOLE DE LUZARCHES",
    "adresse": "4 BIS RUE CHARLES DE GAULLE",
    "cp": 95270,
    "tauxa1": "",
    "tauxa2": "",
    "tauxb": "",
    "tauxb1": "",
    "tauxbe": "",
    "tauxc1": "",
    "tauxce": "",
    "tauxd": "",
    "ville": "LUZARCHES",
    "label_qualite": "Oui",
    "permis_1euro_jour": "Oui",
    "permis_A": "Oui",
    "permis_A1": "Oui",
    "permis_A2": "Oui",
    "permis_B": "Oui",
    "permis_BE": "Oui",
    "permis_C": "Non",
    "permis_C1": "Non",
    "permis_CE": "Non",
    "permis_C1E": "Non",
    "permis_D": "Non",
    "permis_D1": "Non",
    "permis_DE": "Non",
    "lng": "2.4221358",
    "lat": 49.110644
  },
  {
    "agrement": "E2109500210",
    "raison_sociale": "permis_EXPRESS",
    "adresse": "18 RUE VIVIEN",
    "cp": 95270,
    "tauxa1": "",
    "tauxa2": "",
    "tauxb": "",
    "tauxb1": "",
    "tauxbe": "",
    "tauxc1": "",
    "tauxce": "",
    "tauxd": "",
    "ville": "LUZARCHES",
    "label_qualite": "Oui",
    "permis_1euro_jour": "Oui",
    "permis_A": "Non",
    "permis_A1": "Non",
    "permis_A2": "Non",
    "permis_B": "Oui",
    "permis_BE": "Non",
    "permis_C": "Non",
    "permis_C1": "Non",
    "permis_CE": "Non",
    "permis_C1E": "Non",
    "permis_D": "Non",
    "permis_D1": "Non",
    "permis_DE": "Non",
    "lng": "2.4210852",
    "lat": 49.1140435
  }
]