[
  {
    "raison_sociale": "SAS CONDUIRE AUTREMENT",
    "agrement": "E1505700140",
    "adresse": "80, Grand Rue",
    "cp": "57280",
    "ville": "MAIZIERES LES METZ",
    "tauxa1": "100,00%",
    "tauxa2": "93,33%",
    "tauxb": "51,32%",
    "tauxb1": "",
    "tauxbe": "",
    "tauxc1": "",
    "tauxce": "",
    "tauxd": "",
    "label_qualite": "",
    "permis_1euro_jour": "",
    "permis_A": "",
    "permis_A1": "",
    "permis_A2": "",
    "permis_B": "",
    "permis_BE": "",
    "permis_C": "",
    "permis_C1": "",
    "permis_CE": "",
    "permis_C1E": "",
    "permis_D": "",
    "permis_D1": "",
    "permis_DE": "",
    "lng": "6.1596233",
    "lat": 49.2127718
  },
  {
    "raison_sociale": "CIC",
    "agrement": "E1405700170",
    "adresse": "66, Grand Rue",
    "cp": "57280",
    "ville": "Maizières lès Metz",
    "tauxa1": "",
    "tauxa2": "",
    "tauxb": "0,00%",
    "tauxb1": "",
    "tauxbe": "",
    "tauxc1": "",
    "tauxce": "",
    "tauxd": "",
    "label_qualite": "Oui",
    "permis_1euro_jour": "Oui",
    "permis_A": "Non",
    "permis_A1": "Non",
    "permis_A2": "Non",
    "permis_B": "Oui",
    "permis_BE": "Non",
    "permis_C": "Non",
    "permis_C1": "Non",
    "permis_CE": "Non",
    "permis_C1E": "Non",
    "permis_D": "Non",
    "permis_D1": "Non",
    "permis_DE": "Non",
    "lng": "6.1596233",
    "lat": 49.2127718
  }
]