[
  {
    "raison_sociale": "1ROBLIN MONTVILLE",
    "agrement": "E1207610540",
    "adresse": "1 PLACE DE LA REPUBLIQUE",
    "cp": "76710",
    "ville": "MONTVILLE",
    "tauxa1": "",
    "tauxa2": "",
    "tauxb": "57,14%",
    "tauxb1": "",
    "tauxbe": "",
    "tauxc1": "",
    "tauxce": "",
    "tauxd": "",
    "label_qualite": "",
    "permis_1euro_jour": "",
    "permis_A": "",
    "permis_A1": "",
    "permis_A2": "",
    "permis_B": "",
    "permis_BE": "",
    "permis_C": "",
    "permis_C1": "",
    "permis_CE": "",
    "permis_C1E": "",
    "permis_D": "",
    "permis_D1": "",
    "permis_DE": "",
    "lng": "1.0742272",
    "lat": 49.5483752
  },
  {
    "agrement": "E1707600160",
    "raison_sociale": "OPHEL  SAB",
    "adresse": "32 RUE DELPHIN QUEMIN",
    "cp": 76710,
    "tauxa1": "",
    "tauxa2": "",
    "tauxb": "",
    "tauxb1": "",
    "tauxbe": "",
    "tauxc1": "",
    "tauxce": "",
    "tauxd": "",
    "ville": "MONTVILLE",
    "label_qualite": "Oui",
    "permis_1euro_jour": "Oui",
    "permis_A": "Oui",
    "permis_A1": "Oui",
    "permis_A2": "Oui",
    "permis_B": "Oui",
    "permis_BE": "Oui",
    "permis_C": "Non",
    "permis_C1": "Non",
    "permis_CE": "Non",
    "permis_C1E": "Non",
    "permis_D": "Non",
    "permis_D1": "Non",
    "permis_DE": "Non",
    "lng": "1.0756309",
    "lat": 49.5492713
  }
]