[
  {
    "raison_sociale": "Fit Formation Grand Pascal",
    "agrement": "I1606300040",
    "adresse": "10 bis rue Amable Faucon",
    "cp": "63200",
    "ville": "Riom",
    "tauxa1": "",
    "tauxa2": "",
    "tauxb": "75,00%",
    "tauxb1": "",
    "tauxbe": "",
    "tauxc1": "",
    "tauxce": "",
    "tauxd": "",
    "label_qualite": "",
    "permis_1euro_jour": "",
    "permis_A": "",
    "permis_A1": "",
    "permis_A2": "",
    "permis_B": "",
    "permis_BE": "",
    "permis_C": "",
    "permis_C1": "",
    "permis_CE": "",
    "permis_C1E": "",
    "permis_D": "",
    "permis_D1": "",
    "permis_DE": "",
    "lng": "3.1106535",
    "lat": 45.8875422
  }
]5.8939535
  },
  {
    "raison_sociale": "DE LAMBERT ANAIS  Form Riom Comb",
    "agrement": "E1706300090",
    "adresse": "108 Avenue de la Libération",
    "cp": "63200",
    "ville": "RIOM",
    "tauxa1": "",
    "tauxa2": "",
    "tauxb": "64,29%",
    "tauxb1": "",
    "tauxbe": "",
    "tauxc1": "",
    "tauxce": "",
    "tauxd": "",
    "label_qualite": "",
    "permis_1euro_jour": "",
    "permis_A": "",
    "permis_A1": "",
    "permis_A2": "",
    "permis_B": "",
    "permis_BE": "",
    "permis_C": "",
    "permis_C1": "",
    "permis_CE": "",
    "permis_C1E": "",
    "permis_D": "",
    "permis_D1": "",
    "permis_DE": "",
    "lng": "3.1132994",
    "lat": 45.8902566
  },
  {
    "raison_sociale": "DELAMBERT BERNARD",
    "agrement": "E0206306000",
    "adresse": "180                             AVENUE DE LA LIBERATION",
    "cp": "63200",
    "ville": "RIOM",
    "tauxa1": "",
    "tauxa2": "",
    "tauxb": "72,73%",
    "tauxb1": "",
    "tauxbe": "",
    "tauxc1": "",
    "tauxce": "",
    "tauxd": "",
    "label_qualite": "",
    "permis_1euro_jour": "",
    "permis_A": "",
    "permis_A1": "",
    "permis_A2": "",
    "permis_B": "",
    "permis_BE": "",
    "permis_C": "",
    "permis_C1": "",
    "permis_CE": "",
    "permis_C1E": "",
    "permis_D": "",
    "permis_D1": "",
    "permis_DE": "",
    "lng": "3.1132994",
    "lat": 45.8902566
  },
  {
    "raison_sociale": "RIVES JEAN FRANCOIS",
    "agrement": "E0406343250",
    "adresse": "3 AVENUE DE CLERMONT",
    "cp": "63500",
    "ville": "RIOM",
    "tauxa1": "90,00%",
    "tauxa2": "100,00%",
    "tauxb": "71,39%",
    "tauxb1": "",
    "tauxbe": "",
    "tauxc1": "",
    "tauxce": "",
    "tauxd": "",
    "label_qualite": "",
    "permis_1euro_jour": "",
    "permis_A": "",
    "permis_A1": "",
    "permis_A2": "",
    "permis_B": "",
    "permis_BE": "",
    "permis_C": "",
    "permis_C1": "",
    "permis_CE": "",
    "permis_C1E": "",
    "permis_D": "",
    "permis_D1": "",
    "permis_DE": "",
    "lng": "3.0520384",
    "lat": 45.8276562
  },
  {
    "agrement": "E0306307690",
    "raison_sociale": "CER LES VOLCANS",
    "adresse": "10, PLACE JEAN-BAPTISTE LAURENT",
    "cp": 63200,
    "tauxa1": "",
    "tauxa2": "",
    "tauxb": "",
    "tauxb1": "",
    "tauxbe": "",
    "tauxc1": "",
    "tauxce": "",
    "tauxd": "",
    "ville": "RIOM",
    "label_qualite": "Oui",
    "permis_1euro_jour": "Oui",
    "permis_A": "Oui",
    "permis_A1": "Oui",
    "permis_A2": "Oui",
    "permis_B": "Oui",
    "permis_BE": "Oui",
    "permis_C": "Non",
    "permis_C1": "Non",
    "permis_CE": "Non",
    "permis_C1E": "Non",
    "permis_D": "Non",
    "permis_D1": "Non",
    "permis_DE": "Non",
    "lng": "3.1132204",
    "lat": 45.8903337
  }
]