[
  {
    "raison_sociale": "MARGELY",
    "agrement": "E0203505200",
    "adresse": "15 Rue de Merdrignac",
    "cp": "35290",
    "ville": "SAINT-MEEN-LE-GRAND",
    "tauxa1": "",
    "tauxa2": "",
    "tauxb": "",
    "tauxb1": "",
    "tauxbe": "",
    "tauxc1": "",
    "tauxce": "",
    "tauxd": "",
    "label_qualite": "",
    "permis_1euro_jour": "",
    "permis_A": "",
    "permis_A1": "",
    "permis_A2": "",
    "permis_B": "",
    "permis_BE": "",
    "permis_C": "",
    "permis_C1": "",
    "permis_CE": "",
    "permis_C1E": "",
    "permis_D": "",
    "permis_D1": "",
    "permis_DE": "",
    "lng": "-2.1972062",
    "lat": 48.189237
  },
  {
    "raison_sociale": "UDIN ST-MEEN",
    "agrement": "E0403506540",
    "adresse": "3 PLACE PATTON",
    "cp": "35290",
    "ville": "SAINT-MEEN-LE-GRAND",
    "tauxa1": "",
    "tauxa2": "",
    "tauxb": "",
    "tauxb1": "",
    "tauxbe": "",
    "tauxc1": "",
    "tauxce": "",
    "tauxd": "",
    "label_qualite": "",
    "permis_1euro_jour": "",
    "permis_A": "",
    "permis_A1": "",
    "permis_A2": "",
    "permis_B": "",
    "permis_BE": "",
    "permis_C": "",
    "permis_C1": "",
    "permis_CE": "",
    "permis_C1E": "",
    "permis_D": "",
    "permis_D1": "",
    "permis_DE": "",
    "lng": "-2.191603",
    "lat": 48.1889695
  },
  {
    "agrement": "E0203505200",
    "raison_sociale": "BAACALA",
    "adresse": "15 RUE DE MERDRIGNAC",
    "cp": 35290,
    "tauxa1": "",
    "tauxa2": "",
    "tauxb": "",
    "tauxb1": "",
    "tauxbe": "",
    "tauxc1": "",
    "tauxce": "",
    "tauxd": "",
    "ville": "SAINT-MEEN-LE-GRAND",
    "label_qualite": "Oui",
    "permis_1euro_jour": "Oui",
    "permis_A": "Oui",
    "permis_A1": "Oui",
    "permis_A2": "Oui",
    "permis_B": "Oui",
    "permis_BE": "Non",
    "permis_C": "Non",
    "permis_C1": "Non",
    "permis_CE": "Non",
    "permis_C1E": "Non",
    "permis_D": "Non",
    "permis_D1": "Non",
    "permis_DE": "Non",
    "lng": "-2.1972062",
    "lat": 48.189237
  },
  {
    "agrement": "E0403506540",
    "raison_sociale": "UDIN",
    "adresse": "3 PLACE PATTON",
    "cp": 35290,
    "tauxa1": "",
    "tauxa2": "",
    "tauxb": "",
    "tauxb1": "",
    "tauxbe": "",
    "tauxc1": "",
    "tauxce": "",
    "tauxd": "",
    "ville": "SAINT-MEEN-LE-GRAND",
    "label_qualite": "Oui",
    "permis_1euro_jour": "Oui",
    "permis_A": "Non",
    "permis_A1": "Non",
    "permis_A2": "Non",
    "permis_B": "Oui",
    "permis_BE": "Non",
    "permis_C": "Non",
    "permis_C1": "Non",
    "permis_CE": "Non",
    "permis_C1E": "Non",
    "permis_D": "Non",
    "permis_D1": "Non",
    "permis_DE": "Non",
    "lng": "-2.191603",
    "lat": 48.1889695
  }
]