[
  {
    "raison_sociale": "AUTO MOTO ECOLE DU HAUT PERCHE",
    "agrement": "E1706100040",
    "adresse": "33 Rue du 13 Août 1944",
    "cp": "61190",
    "ville": "TOUROUVRE AU PERCHE",
    "tauxa1": "75,00%",
    "tauxa2": "100,00%",
    "tauxb": "41,86%",
    "tauxb1": "",
    "tauxbe": "",
    "tauxc1": "",
    "tauxce": "",
    "tauxd": "",
    "label_qualite": "",
    "permis_1euro_jour": "",
    "permis_A": "",
    "permis_A1": "",
    "permis_A2": "",
    "permis_B": "",
    "permis_BE": "",
    "permis_C": "",
    "permis_C1": "",
    "permis_CE": "",
    "permis_C1E": "",
    "permis_D": "",
    "permis_D1": "",
    "permis_DE": "",
    "lng": "0.6504685",
    "lat": 48.5905214
  }
]