[
  {
    "raison_sociale": "AE DS CONDUITE",
    "agrement": "E0909342220",
    "adresse": "1 3 PL DEGEYTER",
    "cp": "93420",
    "ville": "VILLEPINTE",
    "tauxa1": "",
    "tauxa2": "",
    "tauxb": "59,74%",
    "tauxb1": "",
    "tauxbe": "",
    "tauxc1": "",
    "tauxce": "",
    "tauxd": "",
    "label_qualite": "",
    "permis_1euro_jour": "",
    "permis_A": "",
    "permis_A1": "",
    "permis_A2": "",
    "permis_B": "",
    "permis_BE": "",
    "permis_C": "",
    "permis_C1": "",
    "permis_CE": "",
    "permis_C1E": "",
    "permis_D": "",
    "permis_D1": "",
    "permis_DE": "",
    "lng": "2.562884511183575",
    "lat": 48.9469971
  },
  {
    "raison_sociale": "PLEINS PHARES",
    "agrement": "E1309300450",
    "adresse": "4 Avenue Philippe de Girard",
    "cp": "93420",
    "ville": "VILLEPINTE",
    "tauxa1": "",
    "tauxa2": "",
    "tauxb": "50,00%",
    "tauxb1": "",
    "tauxbe": "",
    "tauxc1": "",
    "tauxce": "",
    "tauxd": "",
    "label_qualite": "Oui",
    "permis_1euro_jour": "Non",
    "permis_A": "Oui",
    "permis_A1": "Oui",
    "permis_A2": "Oui",
    "permis_B": "Oui",
    "permis_BE": "Oui",
    "permis_C": "Non",
    "permis_C1": "Non",
    "permis_CE": "Non",
    "permis_C1E": "Non",
    "permis_D": "Non",
    "permis_D1": "Non",
    "permis_DE": "Non",
    "lng": "2.5432269",
    "lat": 48.9548117
  },
  {
    "raison_sociale": "PLEINS PHARES",
    "agrement": "E1609300160",
    "adresse": "4 avenue Philippe de Girard",
    "cp": "93420",
    "ville": "VILLEPINTE",
    "tauxa1": "",
    "tauxa2": "",
    "tauxb": "69,23%",
    "tauxb1": "",
    "tauxbe": "",
    "tauxc1": "",
    "tauxce": "",
    "tauxd": "",
    "label_qualite": "Oui",
    "permis_1euro_jour": "Non",
    "permis_A": "Oui",
    "permis_A1": "Oui",
    "permis_A2": "Oui",
    "permis_B": "Oui",
    "permis_BE": "Oui",
    "permis_C": "Non",
    "permis_C1": "Non",
    "permis_CE": "Non",
    "permis_C1E": "Non",
    "permis_D": "Non",
    "permis_D1": "Non",
    "permis_DE": "Non",
    "lng": "2.5432269",
    "lat": 48.9548117
  },
  {
    "raison_sociale": "AUTO MOTO ECOLE CFCVM",
    "agrement": "E1609300230",
    "adresse": "9 RUE DE L EGLISE",
    "cp": "93420",
    "ville": "VILLEPINTE",
    "tauxa1": "",
    "tauxa2": "",
    "tauxb": "55,63%",
    "tauxb1": "",
    "tauxbe": "",
    "tauxc1": "",
    "tauxce": "",
    "tauxd": "",
    "label_qualite": "",
    "permis_1euro_jour": "",
    "permis_A": "",
    "permis_A1": "",
    "permis_A2": "",
    "permis_B": "",
    "permis_BE": "",
    "permis_C": "",
    "permis_C1": "",
    "permis_CE": "",
    "permis_C1E": "",
    "permis_D": "",
    "permis_D1": "",
    "permis_DE": "",
    "lng": "2.5348242",
    "lat": 48.9638329
  },
  {
    "raison_sociale": "DRIVE PLUS 93",
    "agrement": "E1509300370",
    "adresse": "4 AVENUE DU CHEMIN DE FER",
    "cp": "93420",
    "ville": "VILLEPINTE",
    "tauxa1": "",
    "tauxa2": "",
    "tauxb": "70,65%",
    "tauxb1": "",
    "tauxbe": "",
    "tauxc1": "",
    "tauxce": "",
    "tauxd": "",
    "label_qualite": "",
    "permis_1euro_jour": "",
    "permis_A": "",
    "permis_A1": "",
    "permis_A2": "",
    "permis_B": "",
    "permis_BE": "",
    "permis_C": "",
    "permis_C1": "",
    "permis_CE": "",
    "permis_C1E": "",
    "permis_D": "",
    "permis_D1": "",
    "permis_DE": "",
    "lng": "2.5655892",
    "lat": 48.9448889
  },
  {
    "raison_sociale": "AUTO-MOTO-ECOLE INRI'S VILLEPINT",
    "agrement": "E1609300030",
    "adresse": "39 ROUTE DE SEVRAN",
    "cp": "93420",
    "ville": "VILLEPINTE",
    "tauxa1": "",
    "tauxa2": "87,50%",
    "tauxb": "65,57%",
    "tauxb1": "",
    "tauxbe": "",
    "tauxc1": "",
    "tauxce": "",
    "tauxd": "",
    "label_qualite": "",
    "permis_1euro_jour": "",
    "permis_A": "",
    "permis_A1": "",
    "permis_A2": "",
    "permis_B": "",
    "permis_BE": "",
    "permis_C": "",
    "permis_C1": "",
    "permis_CE": "",
    "permis_C1E": "",
    "permis_D": "",
    "permis_D1": "",
    "permis_DE": "",
    "lng": "2.5324673",
    "lat": 48.9520787
  },
  {
    "raison_sociale": "GROUPE AMD AUTO-MOTO ECOLE",
    "agrement": "E1509300020",
    "adresse": "85 AVENUE DES NATIONS",
    "cp": "93420",
    "ville": "VILLEPINTE",
    "tauxa1": "",
    "tauxa2": "100,00%",
    "tauxb": "73,33%",
    "tauxb1": "",
    "tauxbe": "",
    "tauxc1": "",
    "tauxce": "",
    "tauxd": "",
    "label_qualite": "",
    "permis_1euro_jour": "",
    "permis_A": "",
    "permis_A1": "",
    "permis_A2": "",
    "permis_B": "",
    "permis_BE": "",
    "permis_C": "",
    "permis_C1": "",
    "permis_CE": "",
    "permis_C1E": "",
    "permis_D": "",
    "permis_D1": "",
    "permis_DE": "",
    "lng": "2.5100724",
    "lat": 48.9734568
  }
]